setup.cfg
setup.py
uber/__init__.py
uber/braintree.py
uber/client.py
uber/geolocation.py
uber/model_base.py
uber/models.py
uber/settings.py
uber.py.egg-info/PKG-INFO
uber.py.egg-info/SOURCES.txt
uber.py.egg-info/dependency_links.txt
uber.py.egg-info/not-zip-safe
uber.py.egg-info/requires.txt
uber.py.egg-info/top_level.txt